slowfast/__init__.py
slowfast/config/__init__.py
slowfast/config/defaults.py
slowfast/datasets/__init__.py
slowfast/datasets/ava_dataset.py
slowfast/datasets/ava_helper.py
slowfast/datasets/build.py
slowfast/datasets/cv2_transform.py
slowfast/datasets/decoder.py
slowfast/datasets/kinetics.py
slowfast/datasets/loader.py
slowfast/datasets/transform.py
slowfast/datasets/utils.py
slowfast/datasets/video_container.py
slowfast/models/__init__.py
slowfast/models/head_helper.py
slowfast/models/losses.py
slowfast/models/model_builder.py
slowfast/models/nonlocal_helper.py
slowfast/models/optimizer.py
slowfast/models/resnet_helper.py
slowfast/models/stem_helper.py
slowfast/models/video_model_builder.py
slowfast/utils/__init__.py
slowfast/utils/ava_eval_helper.py
slowfast/utils/bn_helper.py
slowfast/utils/c2_model_loading.py
slowfast/utils/checkpoint.py
slowfast/utils/distributed.py
slowfast/utils/env.py
slowfast/utils/logging.py
slowfast/utils/lr_policy.py
slowfast/utils/meters.py
slowfast/utils/metrics.py
slowfast/utils/misc.py
slowfast/utils/multiprocessing.py
slowfast/utils/weight_init_helper.py
slowfast/utils/ava_evaluation/__init__.py
slowfast/utils/ava_evaluation/label_map_util.py
slowfast/utils/ava_evaluation/metrics.py
slowfast/utils/ava_evaluation/np_box_list.py
slowfast/utils/ava_evaluation/np_box_list_ops.py
slowfast/utils/ava_evaluation/np_box_mask_list.py
slowfast/utils/ava_evaluation/np_box_mask_list_ops.py
slowfast/utils/ava_evaluation/np_box_ops.py
slowfast/utils/ava_evaluation/np_mask_ops.py
slowfast/utils/ava_evaluation/object_detection_evaluation.py
slowfast/utils/ava_evaluation/per_image_evaluation.py
slowfast/utils/ava_evaluation/standard_fields.py
slowfast-1.0.dist-info/LICENSE
slowfast-1.0.dist-info/METADATA
slowfast-1.0.dist-info/WHEEL
slowfast-1.0.dist-info/top_level.txt
slowfast-1.0.dist-info/RECORD
